loo/__init__.py
loo/__main__.py
loo/cli.py
loo/commands/__init__.py
loo/commands/generate.py
loo-1.0.0a4.dist-info/LICENSE
loo-1.0.0a4.dist-info/METADATA
loo-1.0.0a4.dist-info/WHEEL
loo-1.0.0a4.dist-info/entry_points.txt
loo-1.0.0a4.dist-info/top_level.txt
loo-1.0.0a4.dist-info/RECORD
