Metadata-Version: 2.1
Name: loo
Version: 1.0.0a4
Summary: LooMan Cli
Home-page: https://github.com/LooMan/looman-cli
Author: Fredrik Larsson
Author-email: larsson.fredrik31@gmail.com
License: MIT
Platform: UNKNOWN
Requires-Dist: click
